elva/__init__.py
elva/auth.py
elva/awareness.py
elva/cli.py
elva/component.py
elva/core.py
elva/log.py
elva/main.py
elva/parser.py
elva/protocol.py
elva/provider.py
elva/renderer.py
elva/server.py
elva/store.py
elva/apps/__init__.py
elva/apps/chat/__init__.py
elva/apps/chat/app.py
elva/apps/chat/cli.py
elva/apps/chat/style.tcss
elva/apps/editor/__init__.py
elva/apps/editor/app.py
elva/apps/editor/cli.py
elva/apps/editor/style.tcss
elva/apps/server/__init__.py
elva/apps/server/app.py
elva/apps/server/cli.py
elva/widgets/__init__.py
elva/widgets/awareness.py
elva/widgets/config.py
elva/widgets/screens.py
elva/widgets/ytextarea/__init__.py
elva/widgets/ytextarea/location.py
elva/widgets/ytextarea/selection.py
elva/widgets/ytextarea/widget.py
elva-0.35.dist-info/licenses/LICENSE
elva-0.35.dist-info/METADATA
elva-0.35.dist-info/WHEEL
elva-0.35.dist-info/entry_points.txt
elva-0.35.dist-info/top_level.txt
elva-0.35.dist-info/RECORD
